graphtransformer_digress/__init__.py
graphtransformer_digress/model.py
graphtransformer_digress-0.2.0.dist-info/licenses/LICENSE
graphtransformer_digress-0.2.0.dist-info/METADATA
graphtransformer_digress-0.2.0.dist-info/WHEEL
graphtransformer_digress-0.2.0.dist-info/top_level.txt
graphtransformer_digress-0.2.0.dist-info/RECORD
